narration/__init__.py
narration/__version__.py
narration/constants.py
narration/debug.py
narration/narration.py
narration/py.typed
narration/_broker/__init__.py
narration/_broker/dispatch_broker.py
narration/_broker/dispatch_status.py
narration/_broker/group_broker.py
narration/_broker/shared_dispatch.py
narration/_debug/__init__.py
narration/_debug/logger.py
narration/_debug/myself.py
narration/_handler/__init__.py
narration/_handler/client/__init__.py
narration/_handler/client/common/__init__.py
narration/_handler/client/common/handler/__init__.py
narration/_handler/client/common/handler/base_client_handler.py
narration/_handler/client/common/thread/__init__.py
narration/_handler/client/common/thread/base_sender_thread.py
narration/_handler/client/native/__init__.py
narration/_handler/client/native/native_client_handler.py
narration/_handler/client/native/native_sender_thread.py
narration/_handler/client/zmq/__init__.py
narration/_handler/client/zmq/zmq_client_handler.py
narration/_handler/client/zmq/zmq_sender_thread.py
narration/_handler/common/__init__.py
narration/_handler/common/callable.py
narration/_handler/common/handler/__init__.py
narration/_handler/common/handler/base_handler.py
narration/_handler/common/misc/__init__.py
narration/_handler/common/misc/op_type.py
narration/_handler/common/native/__init__.py
narration/_handler/common/native/native_socket.py
narration/_handler/common/payload/__init__.py
narration/_handler/common/payload/payload.py
narration/_handler/common/payload/serialization/__init__.py
narration/_handler/common/payload/serialization/generic.py
narration/_handler/common/payload/serialization/record_payload.py
narration/_handler/common/record/__init__.py
narration/_handler/common/record/utils.py
narration/_handler/common/socket/__init__.py
narration/_handler/common/socket/base_socket.py
narration/_handler/common/socket/exception/__init__.py
narration/_handler/common/socket/exception/bindfailedexception.py
narration-0.2.21.dist-info/licenses/LICENSE
narration-0.2.21.dist-info/METADATA
narration-0.2.21.dist-info/WHEEL
narration-0.2.21.dist-info/top_level.txt
narration-0.2.21.dist-info/RECORD
