Metadata-Version: 2.4
Name: narration
Version: 0.2.21
Summary: Narration is a logging library starting a server receiving log records from other process.
Author-email: David Andreoletti <none@provided.yet>
License-Expression: LicenseRef-Proprietary
Project-URL: repository, https://github.com/davidandreoletti/narration
Keywords: narration
Classifier: Development Status :: 4 - Beta
Classifier: Intended Audience :: Developers
Classifier: Natural Language :: English
Classifier: Operating System :: MacOS :: MacOS X
Classifier: Operating System :: POSIX :: Linux
Classifier: Programming Language :: Python
Classifier: Programming Language :: Python :: 3
Classifier: Programming Language :: Python :: 3.10
Classifier: Programming Language :: Python :: 3.11
Classifier: Programming Language :: Python :: 3.12
Classifier: Programming Language :: Python :: 3.13
Classifier: Programming Language :: Python :: 3.14
Requires-Python: <3.15,>=3.10
License-File: LICENSE
Requires-Dist: pyzmq>=23.2.0
Requires-Dist: blinker>=1.4
Requires-Dist: attrs>=20.3.0
Requires-Dist: msgspec>=0.7.1
Requires-Dist: loguru>=0.5.3
Requires-Dist: typing-extensions>=4.3.0
Dynamic: license-file
